cstest1/test1.py
cstest1/test2.py
cstest1/testprojects.py
cstest1-0.0.0.2.dist-info/METADATA
cstest1-0.0.0.2.dist-info/WHEEL
cstest1-0.0.0.2.dist-info/top_level.txt
cstest1-0.0.0.2.dist-info/RECORD
