Metadata-Version: 2.1
Name: cstest1
Version: 0.0.0.2
Summary: My First Test Package
Home-page: https://blog.naver.com/fpqaut
Author: Demeno
Author-email: fpqaut@naver.com
License: MIT
Platform: UNKNOWN
Requires-Python: >=3
